gym_dcmotor/__init__.py
gym_dcmotor/envs/__init__.py
gym_dcmotor/envs/dcmotor_env.py
gym_dcmotor/envs/numapp.py
gym_dcmotor-0.2.dist-info/licenses/LICENSE
gym_dcmotor-0.2.dist-info/METADATA
gym_dcmotor-0.2.dist-info/WHEEL
gym_dcmotor-0.2.dist-info/top_level.txt
gym_dcmotor-0.2.dist-info/RECORD
