Metadata-Version: 2.4
Name: gym_dcmotor
Version: 0.2
Summary: A simple DC motor environment for reinforcement learning
Home-page: https://github.com/llewynS/dcmotorenv
Author: LlewynS
Author-email: algos251@gmail.com
License: GNUAGPLv3
License-File: LICENSE
Requires-Dist: gymnasium
Requires-Dist: numpy
Requires-Dist: matplotlib
Dynamic: author
Dynamic: author-email
Dynamic: description
Dynamic: description-content-type
Dynamic: home-page
Dynamic: license
Dynamic: license-file
Dynamic: requires-dist
Dynamic: summary
